hideip/__init__.py
hideip/hideip.py
hideip-0.1.0.dist-info/LICENSE
hideip-0.1.0.dist-info/METADATA
hideip-0.1.0.dist-info/WHEEL
hideip-0.1.0.dist-info/top_level.txt
hideip-0.1.0.dist-info/RECORD
