Metadata-Version: 2.1
Name: hideip
Version: 0.1.0
Summary: Hide your IP from the Internet
Home-page: https://github.com/tquangsdh20/hideip
Author: Joseph Quang
Author-email: tquang.sdh20@hcmut.edu.vn
License: Apache 2.0
Platform: unix
Platform: linux
Platform: osx
Platform: cygwin
Platform: win32
Platform: macOS
Classifier: Intended Audience :: Education
Classifier: Intended Audience :: End Users/Desktop
Classifier: Development Status :: 5 - Production/Stable
Classifier: Operating System :: OS Independent
Classifier: License :: OSI Approved :: Apache Software License
Classifier: Programming Language :: Python :: 3
Classifier: Programming Language :: Python :: 3.6
Classifier: Programming Language :: Python :: 3.7
Classifier: Programming Language :: Python :: 3.8
Classifier: Programming Language :: Python :: 3.9
Requires-Dist: requests (>=2.23)
Requires-Dist: PySocks (>=1.7)
